gql-graphene_django_subscriptions/__init__.py
gql-graphene_django_subscriptions/bindings.py
gql-graphene_django_subscriptions/consumers.py
gql-graphene_django_subscriptions/middleware.py
gql-graphene_django_subscriptions/mixins.py
gql-graphene_django_subscriptions/subscription.py
graphene_django_subscriptions/__init__.py
graphene_django_subscriptions/bindings.py
graphene_django_subscriptions/consumers.py
graphene_django_subscriptions/middleware.py
graphene_django_subscriptions/mixins.py
graphene_django_subscriptions/subscription.py
gql_graphene_django_subscriptions-0.0.7.dist-info/LICENSE
gql_graphene_django_subscriptions-0.0.7.dist-info/METADATA
gql_graphene_django_subscriptions-0.0.7.dist-info/WHEEL
gql_graphene_django_subscriptions-0.0.7.dist-info/top_level.txt
gql_graphene_django_subscriptions-0.0.7.dist-info/RECORD
