Metadata-Version: 2.1
Name: gql-graphene-django-subscriptions
Version: 0.0.7
Summary: Graphene-Django-Subscriptions add subscriptions support to graphene-django through Channels module
Home-page: https://github.com/eamigo86/graphene-django-subscriptions
Author: Levi Notik
Author-email: levi@greatjones.co
License: MIT
Keywords: api graphql subscription rest graphene django channels
Platform: any
Classifier: Intended Audience :: Developers
Classifier: Topic :: Software Development :: Libraries
Classifier: Programming Language :: Python :: 2
Classifier: Programming Language :: Python :: 2.7
Classifier: Programming Language :: Python :: 3
Classifier: Programming Language :: Python :: 3.3
Classifier: Programming Language :: Python :: 3.4
Classifier: Programming Language :: Python :: 3.5
Classifier: Programming Language :: Python :: 3.6
Classifier: Programming Language :: Python :: 3.7
Classifier: Programming Language :: Python :: Implementation :: PyPy
Requires-Dist: graphene-django (==2.6.0)
Requires-Dist: graphene-django-extras (>=0.3.0)
Requires-Dist: channels-api (>=0.4.0)
